taskdaily/__init__.py
taskdaily/__main__.py
taskdaily/task_manager.py
taskdaily/version.py
taskdaily/cli/__init__.py
taskdaily/cli/main.py
taskdaily/config/__init__.py
taskdaily/config/config_manager.py
taskdaily/core/__init__.py
taskdaily/core/interfaces/formatter.py
taskdaily/core/interfaces/storage.py
taskdaily/core/models/__init__.py
taskdaily/core/models/project.py
taskdaily/core/models/task.py
taskdaily/exceptions/__init__.py
taskdaily/exceptions/base.py
taskdaily/formatters/__init__.py
taskdaily/formatters/email.py
taskdaily/formatters/factory.py
taskdaily/formatters/slack.py
taskdaily/formatters/teams.py
taskdaily/formatters/whatsapp.py
taskdaily/handlers/__init__.py
taskdaily/handlers/base.py
taskdaily/handlers/slack.py
taskdaily/handlers/formatters/__init__.py
taskdaily/handlers/formatters/base_formatter.py
taskdaily/handlers/formatters/email_formatter.py
taskdaily/handlers/formatters/slack_formatter.py
taskdaily/handlers/formatters/teams_formatter.py
taskdaily/handlers/formatters/whatsapp_formatter.py
taskdaily/storage/__init__.py
taskdaily/storage/factory.py
taskdaily/storage/file_storage.py
taskdaily/templates/config.yaml
taskdaily/templates/daily_template.md
taskdaily/utils/__init__.py
taskdaily/utils/date.py
taskdaily/utils/text.py
taskdaily-2.0.3.dist-info/licenses/LICENSE
taskdaily-2.0.3.dist-info/METADATA
taskdaily-2.0.3.dist-info/WHEEL
taskdaily-2.0.3.dist-info/entry_points.txt
taskdaily-2.0.3.dist-info/top_level.txt
taskdaily-2.0.3.dist-info/RECORD
