Metadata-Version: 2.4
Name: taskdaily
Version: 2.0.3
Summary: A flexible daily task management system with customizable templates
Home-page: https://github.com/nainesh-rabadiya/taskdaily
Author: Nainesh Rabadiya
Author-email: Nainesh Rabadiya <nkrabadiya@gmail.com>
License-Expression: MIT
Project-URL: Homepage, https://github.com/nainesh-rabadiya/taskdaily
Project-URL: Repository, https://github.com/nainesh-rabadiya/taskdaily.git
Keywords: task-management daily-tasks project-management productivity
Classifier: Development Status :: 4 - Beta
Classifier: Intended Audience :: Developers
Classifier: Topic :: Office/Business :: Scheduling
Classifier: Topic :: Software Development :: Libraries :: Python Modules
Classifier: Operating System :: OS Independent
Requires-Python: >=3.8
License-File: LICENSE
Requires-Dist: click>=8.0.0
Requires-Dist: PyYAML>=6.0.0
Requires-Dist: rich>=10.0.0
Requires-Dist: pyperclip>=1.8.0
Dynamic: author
Dynamic: home-page
Dynamic: keywords
Dynamic: license-file
Dynamic: requires-python
